pypaperwallet
