Metadata-Version: 2.1
Name: pypaperwallet
Version: 0.3
Summary: Python Paper Wallet
Home-page: https://github.com/brianddk/pypaperwallet
Author: brianddk
Author-email: brianddk@users.noreply.github.com
License: Apache License 2.0
Project-URL: Bug Reports, https://github.com/brianddk/pypaperwallet/issues
Project-URL: Source, https://github.com/brianddk/pypaperwallet
Keywords: paperwallet,bitcoin
Platform: UNKNOWN
Classifier: License :: OSI Approved :: Apache Software License
Classifier: Programming Language :: Python :: 3
Classifier: Programming Language :: Python :: 3.7
Classifier: Programming Language :: Python :: 3.8
Requires-Python: >=3.7.1
